glue_statswidget/__init__.py
glue_statswidget/statistics.py
glue_statswidget/version.py
glue_statswidget-0.0.dev0.dist-info/LICENSE
glue_statswidget-0.0.dev0.dist-info/METADATA
glue_statswidget-0.0.dev0.dist-info/WHEEL
glue_statswidget-0.0.dev0.dist-info/entry_points.txt
glue_statswidget-0.0.dev0.dist-info/top_level.txt
glue_statswidget-0.0.dev0.dist-info/RECORD
