Metadata-Version: 2.1
Name: glue-statswidget
Version: 0.0.dev0
Summary: A Statistics Widget for Glue
Home-page: https://github.com/glue-viz/glue-plugin-template
Author: Laura Chapman & Catherine Zucker
Author-email: catherine.zucker@cfa.harvard.edu
License: UNKNOWN
Platform: UNKNOWN
